{
  "run_id": "reply-20260715-2320",
  "revision": 1,
  "verdict": "PASS",
  "findings": [],
  "stats": {
    "sections_checked": 6,
    "violations": 0,
    "violations_by_type": {
      "STRUCTURE": 0,
      "STYLE": 0,
      "TONE": 0,
      "SENSITIVE": 0
    }
  },
  "notes": {
    "resolved_from_revision_0": "STYLE 지적 1건(2.다.1) 과장어 '비약적') — 보도자료 원문 직접인용(따옴표+귀속 명시)으로 전환되어 해소 확인.",
    "structure": "두괄식(1. 답변 요지 선행), 1.→가.→1) 항목 체계, 요지·인용 출처 필수 섹션 모두 충족.",
    "style": "개조식(~함/~임/~됨) 종결 일관. 과장어·헤지 겹침·번역투 없음. '도약의 발판' 등 수사적 표현은 전부 직접인용 내부로 답변 본문 문체와 분리됨.",
    "tone": "'~하겠다' 표현은 전부 청장 발언 직접인용 또는 보도자료 귀속 간접화법으로 단정적 약속 아님. 비공개 사항(협상 전략·계약 조건) 답변 생략 문구 유지. 타 기관 소관 월권 답변 없음. 질의의 '심의·의결'을 법문상 '심의·조정'으로 바로잡은 처리도 적절함.",
    "sensitive": "sensitive_terms.json 9개 민감어 미출현. 재작성에서 추가·수정된 내용(제9조제2항 15개 항목 표기, 위원 위촉 요건 상세, 시행령 제13조 위원 범위)은 모두 공개 법령 조문 범위이며 맥락상 민감정보 아님. 예산 수치(약 500억 원)·인명(방위사업청장)도 공개 보도자료 출처."
  }
}
